durabletask/azuremanaged/__init__.py
durabletask/azuremanaged/client.py
durabletask/azuremanaged/py.typed
durabletask/azuremanaged/worker.py
durabletask/azuremanaged/internal/access_token_manager.py
durabletask/azuremanaged/internal/durabletask_grpc_interceptor.py
durabletask/azuremanaged/internal/py.typed
durabletask_azuremanaged-1.0.0.dist-info/METADATA
durabletask_azuremanaged-1.0.0.dist-info/WHEEL
durabletask_azuremanaged-1.0.0.dist-info/top_level.txt
durabletask_azuremanaged-1.0.0.dist-info/RECORD
