Metadata-Version: 2.4
Name: durabletask.azuremanaged
Version: 1.0.0
Summary: Durable Task Python SDK provider implementation for the Azure Durable Task Scheduler
Project-URL: repository, https://github.com/microsoft/durabletask-python
Project-URL: changelog, https://github.com/microsoft/durabletask-python/blob/main/CHANGELOG.md
Keywords: durable,task,workflow,azure
Classifier: Development Status :: 5 - Production/Stable
Classifier: Programming Language :: Python :: 3
Classifier: License :: OSI Approved :: MIT License
Requires-Python: >=3.10
Requires-Dist: durabletask>=1.0.0
Requires-Dist: azure-identity>=1.19.0
